ilionx_filtered_faiss_lookup/__init__.py
ilionx_filtered_faiss_lookup/tools/__init__.py
ilionx_filtered_faiss_lookup/tools/filtered_faiss_lookup.py
ilionx_filtered_faiss_lookup/tools/utils.py
ilionx_filtered_faiss_lookup/yamls/filtered_faiss_lookup.yaml
tests/__init__.py
tests/test_filtered_faiss_lookup.py
ilionx_filtered_faiss_lookup-0.0.2.dist-info/METADATA
ilionx_filtered_faiss_lookup-0.0.2.dist-info/WHEEL
ilionx_filtered_faiss_lookup-0.0.2.dist-info/entry_points.txt
ilionx_filtered_faiss_lookup-0.0.2.dist-info/top_level.txt
ilionx_filtered_faiss_lookup-0.0.2.dist-info/RECORD
